duka_dl/__init__.py
duka_dl-0.1.1.dist-info/entry_points.txt
duka_dl-0.1.1.dist-info/licenses/LICENSE
duka_dl-0.1.1.dist-info/METADATA
duka_dl-0.1.1.dist-info/WHEEL
duka_dl-0.1.1.dist-info/RECORD
