Metadata-Version: 2.4
Name: duka_dl
Version: 0.1.1
Summary: A fast and simple downloader for Dukascopy
License: MIT License
License-File: LICENSE
Author: Trần Đình Nguyên
Author-email: nguyentd010@gmail.com
Requires-Python: >=3.10
Classifier: Programming Language :: Python :: 3
Classifier: License :: OSI Approved :: MIT License
Classifier: Operating System :: OS Independent
Requires-Dist: httpx (>=0.28.1,<0.29.0)
Requires-Dist: polars (>=1.33.1,<2.0.0)
Requires-Dist: rich-argparse (>=1.7.1,<2.0.0)
Requires-Dist: tqdm (>=4.67.1,<5.0.0)
